gitsnitch/__init__.py
gitsnitch/__version__.py
gitsnitch/cli.py
gitsnitch-1.0.4.dist-info/LICENSE.txt
gitsnitch-1.0.4.dist-info/METADATA
gitsnitch-1.0.4.dist-info/WHEEL
gitsnitch-1.0.4.dist-info/entry_points.txt
gitsnitch-1.0.4.dist-info/top_level.txt
gitsnitch-1.0.4.dist-info/RECORD
